xsellco_api/__init__.py
xsellco_api/base.py
xsellco_api/exceptions.py
xsellco_api/info.py
xsellco_api/api/__init__.py
xsellco_api/api/channels.py
xsellco_api/api/repricers.py
xsellco_api/api/users.py
xsellco_api/async_/__init__.py
xsellco_api/async_/asyncchannels.py
xsellco_api/async_/asyncrepricers.py
xsellco_api/async_/asyncusers.py
xsellco_api/async_/client.py
xsellco_api/common/__init__.py
xsellco_api/common/base.py
xsellco_api/common/utils.py
xsellco_api/sync/__init__.py
xsellco_api/sync/channels.py
xsellco_api/sync/client.py
xsellco_api/sync/repricers.py
xsellco_api/sync/users.py
xsellco_api-0.0.9.dist-info/LICENSE
xsellco_api-0.0.9.dist-info/METADATA
xsellco_api-0.0.9.dist-info/WHEEL
xsellco_api-0.0.9.dist-info/top_level.txt
xsellco_api-0.0.9.dist-info/RECORD
