Metadata-Version: 2.1
Name: xsellco_api
Version: 0.0.9
Summary: Wrapper around Repricer.com API (aka Xsellco)
Home-page: https://github.com/yberezkin/xsellco-api
Author: Yan Berezkin
Author-email: yan.berezkin@gmail.com
License: MIT
Project-URL: Bug Tracker, https://github.com/yberezkin/xsellco-api/issues
Keywords: xsellco,repricer
Requires-Python: >=3.9
License-File: LICENSE
Requires-Dist: requests>=2.30.0
Requires-Dist: httpx>=0.18.0
